odict/__init__.py
odict/bench.py
odict/pyodict.py
odict/tests.py
odict-1.9.0.dist-info/LICENSE.rst
odict-1.9.0.dist-info/METADATA
odict-1.9.0.dist-info/WHEEL
odict-1.9.0.dist-info/namespace_packages.txt
odict-1.9.0.dist-info/top_level.txt
odict-1.9.0.dist-info/zip-safe
odict-1.9.0.dist-info/RECORD
