Metadata-Version: 1.1
Name: odict
Version: 1.9.0
Summary: Ordered Dictionary.
Home-page: https://github.com/conestack/odict
Author: Node Contributors
Author-email: dev@conestack.org
License: Python Software Foundation License
Keywords: odict dict ordered dictionary mapping collection tree
Platform: UNKNOWN
Classifier: Development Status :: 5 - Production/Stable
Classifier: License :: OSI Approved :: Python Software Foundation License
Classifier: Operating System :: OS Independent
Classifier: Topic :: Software Development
Classifier: Programming Language :: Python
Classifier: Programming Language :: Python :: 2.7
Classifier: Programming Language :: Python :: 3.7
Classifier: Programming Language :: Python :: 3.8
Classifier: Programming Language :: Python :: 3.9
Classifier: Programming Language :: Python :: 3.10
